opslib/__init__.py
opslib/ansible.py
opslib/callbacks.py
opslib/cli.py
opslib/components.py
opslib/lazy.py
opslib/local.py
opslib/operations.py
opslib/places.py
opslib/props.py
opslib/results.py
opslib/state.py
opslib/terraform.py
opslib/uptodate.py
opslib/utils.py
opslib/extras/http.py
opslib/extras/restic.py
opslib/extras/systemd.py
opslib/extras/tailscale.py
pyopslib-0.2.dist-info/entry_points.txt
pyopslib-0.2.dist-info/LICENSE
pyopslib-0.2.dist-info/WHEEL
pyopslib-0.2.dist-info/METADATA
pyopslib-0.2.dist-info/RECORD
