Metadata-Version: 2.1
Name: pyopslib
Version: 0.2
Summary: A Pythonic toolkit to manage infrastructure.
Author-email: Alex Morega <alex@grep.ro>
Requires-Python: >=3.12
Requires-Dist: ansible-core>=2.14.3,<2.15
Requires-Dist: beartype>=0.12.0
Requires-Dist: click>=8.1.3
Requires-Dist: requests>=2.28.2
Requires-Dist: flit>=3.2,<4 ; extra == "dev"
Requires-Dist: keyring>=24.3.0 ; extra == "dev"
Requires-Dist: pyright>=1.1.337 ; extra == "dev"
Requires-Dist: pytest-black-ng>=0.4.1 ; extra == "dev"
Requires-Dist: pytest-isort>=3.1.0 ; extra == "dev"
Requires-Dist: pytest>=7.2.2 ; extra == "dev"
Requires-Dist: sphinx-autobuild>=2021.3.14 ; extra == "dev"
Requires-Dist: sphinx>=6.1.3 ; extra == "dev"
Provides-Extra: dev
